VideoGameDay/__init__.py
VideoGameDay/fun_fact_rand/__init__.py
VideoGameDay/fun_fact_rand/fun_facts.py
VideoGameDay/fun_fact_rand/fun_facts_db.py
VideoGameDay/gaming_luck/__init__.py
VideoGameDay/gaming_luck/gaming_luck.py
VideoGameDay/gaming_luck/luck_data.py
VideoGameDay/guess_game/__init__.py
VideoGameDay/guess_game/cli.py
VideoGameDay/guess_game/game_data.py
VideoGameDay/guess_game/guesser.py
VideoGameDay/recommend_game/__init__.py
VideoGameDay/recommend_game/game_data.py
VideoGameDay/recommend_game/recommend_game.py
videogameday-0.1.4.dist-info/licenses/LICENSE
videogameday-0.1.4.dist-info/METADATA
videogameday-0.1.4.dist-info/WHEEL
videogameday-0.1.4.dist-info/top_level.txt
videogameday-0.1.4.dist-info/RECORD
