Metadata-Version: 2.4
Name: VideoGameDay
Version: 0.1.4
Summary: A fun package for video game recommendations, trivia, guessing, and luck prediction
Author-email: Lily Fu <jf4296@nyu.edu>, Jialiang Tang <jt4260@nyu.edu>, Peng Jiang <pj2196@nyu.edu>, Adam Cao <jc9770@nyu.edu>
License-Expression: GPL-3.0-or-later
Project-URL: Homepage, https://github.com/software-students-spring2025/3-python-package-atajo-devs
Project-URL: Repository, https://github.com/software-students-spring2025/3-python-package-atajo-devs
Project-URL: Issues, https://github.com/software-students-spring2025/3-python-package-atajo-devs/issues
Keywords: game,fortune,fun,gaming,guessing,trivia,luck
License-File: LICENSE
Provides-Extra: dev
Requires-Dist: pytest; extra == "dev"
Dynamic: license-file
